purecpp_imports_test/__init__.py
purecpp_imports_test-0.0.1.dist-info/METADATA
purecpp_imports_test-0.0.1.dist-info/WHEEL
purecpp_imports_test-0.0.1.dist-info/top_level.txt
purecpp_imports_test-0.0.1.dist-info/RECORD
