Metadata-Version: 2.2
Name: purecpp_imports_test
Version: 0.0.1
Summary: This package is a part of the PureCPP ecosyste.
Home-page: https://github.com/pureai-ecosystem/purecpp
Author: Diogo Vieira
Author-email: contato@pureai.com.br
Classifier: Programming Language :: Python :: 3
Classifier: Operating System :: POSIX :: Linux
Requires-Dist: purecpp_libs
Requires-Dist: auditwheel
Requires-Dist: build
Requires-Dist: requests
Requires-Dist: wheel
Requires-Dist: pybind11
Requires-Dist: setuptools
Requires-Dist: purecpp_extract
Requires-Dist: purecpp_embed
Requires-Dist: purecpp_meta
Requires-Dist: purecpp_chunks_clean
Dynamic: author
Dynamic: author-email
Dynamic: classifier
Dynamic: home-page
Dynamic: requires-dist
Dynamic: summary
